metadpy/__init__.py
metadpy/bayesian.py
metadpy/mle.py
metadpy/plotting.py
metadpy/sdt.py
metadpy/utils.py
metadpy/datasets/__init__.py
metadpy/models/subject_level_pymc.py
metadpy-0.1.2.dist-info/LICENSE
metadpy-0.1.2.dist-info/METADATA
metadpy-0.1.2.dist-info/WHEEL
metadpy-0.1.2.dist-info/top_level.txt
metadpy-0.1.2.dist-info/RECORD
