Metadata-Version: 2.1
Name: metadpy
Version: 0.1.2
Summary: metadpy: Metacognitive efficiency modelling in Python
Home-page: https://github.com/LegrandNico/metadpy
Author: Nicolas Legrand
Author-email: nicolas.legrand@cas.au.dk
Maintainer: Nicolas Legrand
Maintainer-email: nicolas.legrand@cas.au.dk
License: GPL-3.0
License-File: LICENSE
Requires-Dist: numpy >=1.17
Requires-Dist: scipy >=1.3.0
Requires-Dist: pandas >=0.24
Requires-Dist: matplotlib >=3.0.2
Requires-Dist: seaborn >=0.9.0
Requires-Dist: pandas-flavor >=0.2.0
Requires-Dist: numba >=0.55.1
Requires-Dist: tqdm
